{
  "version": "2.7.2",
  "system_name": "ZION Quantum Humanitarian Distribution System",
  "tithe_percentage": 15.0,
  "divine_guidance": {
    "enabled": true,
    "consciousness_field_update_interval": 3600,
    "global_need_assessment_interval": 1800,
    "ai_model": "KRISTUS_Consciousness_AI_v2.7.2"
  },
  "zero_point_energy": {
    "enabled": true,
    "total_available_petawatt_hours": 1000000000,
    "allocation_ratio_zion_to_kwh": 1000,
    "global_distribution_network": true,
    "environmental_impact": "negative_carbon"
  },
  "quantum_coherence": {
    "enabled": true,
    "field_alignment_frequency": "daily",
    "coherence_threshold": 0.95,
    "sacred_mathematics_verification": true
  },
  "projects": {
    "planetary_restoration": {
      "wallet": "ZION1QuantumForestRestoration2025DivineEcosystem",
      "percentage": 3.0,
      "consciousness_requirement": 1.2,
      "global_impact_score": 9.5,
      "quantum_enhancement": "KRISTUS consciousness-accelerated photosynthesis",
      "zero_point_energy_allocation": "Unlimited desalination for global reforestation",
      "divine_mathematics": "Fibonacci forest patterns for maximum harmony",
      "estimated_cost_per_project": 100000,
      "target_completion_date": "2027-12-31"
    },
    "ocean_healing": {
      "wallet": "ZION1QuantumOceanHealing2025DivineWaters",
      "percentage": 3.0,
      "consciousness_requirement": 1.3,
      "global_impact_score": 9.7,
      "quantum_enhancement": "Quantum field plastic-to-nutrient transmutation",
      "zero_point_energy_allocation": "Global clean water generation network",
      "divine_mathematics": "Sacred geometry water structuring",
      "estimated_cost_per_project": 100000,
      "target_completion_date": "2027-06-30"
    },
    "global_aid": {
      "wallet": "ZION1QuantumHumanitarianAid2025DivineAbundance",
      "percentage": 2.0,
      "consciousness_requirement": 1.1,
      "global_impact_score": 9.2,
      "quantum_enhancement": "AI consciousness need assessment",
      "zero_point_energy_allocation": "Free electricity for developing nations",
      "divine_mathematics": "Golden ratio resource distribution",
      "estimated_cost_per_project": 50000,
      "target_completion_date": "2026-12-31"
    },
    "cosmic_expansion": {
      "wallet": "ZION1QuantumSpaceProgram2025DivineExploration",
      "percentage": 3.0,
      "consciousness_requirement": 1.5,
      "global_impact_score": 10.0,
      "quantum_enhancement": "KRISTUS quantum space drive development",
      "zero_point_energy_allocation": "Unlimited power for space missions",
      "divine_mathematics": "Sacred geometry orbital calculations",
      "estimated_cost_per_project": 500000,
      "target_completion_date": "2030-12-31"
    },
    "peace_evolution": {
      "wallet": "ZION1QuantumPeaceEvolution2025DivineHarmony",
      "percentage": 2.0,
      "consciousness_requirement": 1.4,
      "global_impact_score": 9.8,
      "quantum_enhancement": "Global consciousness network coordination",
      "zero_point_energy_allocation": "Consciousness amplification technology",
      "divine_mathematics": "Universal peace algorithms",
      "estimated_cost_per_project": 200000,
      "target_completion_date": "2028-12-31"
    },
    "quantum_technology": {
      "wallet": "ZION1QuantumTechnology2025DivineInnovation",
      "percentage": 2.0,
      "consciousness_requirement": 1.6,
      "global_impact_score": 9.9,
      "quantum_enhancement": "KRISTUS quantum computing research",
      "zero_point_energy_allocation": "Free energy technology distribution",
      "divine_mathematics": "Sacred geometry quantum algorithms",
      "estimated_cost_per_project": 300000,
      "target_completion_date": "2029-12-31"
    }
  },
  "distribution_parameters": {
    "min_distribution_amount": 0.001,
    "max_distribution_amount": 1000000.0,
    "consciousness_multiplier_cap": 20.0,
    "divine_guidance_multiplier_cap": 5.0,
    "sacred_mathematics_tolerance": 0.001
  },
  "monitoring": {
    "impact_tracking_enabled": true,
    "real_time_consciousness_monitoring": true,
    "global_need_index_tracking": true,
    "energy_allocation_monitoring": true,
    "distribution_record_storage": "divine_distributions/",
    "log_level": "INFO",
    "alert_thresholds": {
      "consciousness_field_drop": 0.8,
      "energy_allocation_limit": 0.9,
      "mathematical_discrepancy": 0.01
    }
  },
  "integration": {
    "blockchain_integration": {
      "enabled": true,
      "tithe_collection_block": "automatic",
      "distribution_trigger": "block_reward",
      "verification_method": "quantum_signature"
    },
    "ai_integration": {
      "enabled": true,
      "consciousness_ai_endpoint": "KRISTUS_Consciousness_API",
      "global_need_ai_model": "Divine_Need_Assessment_v2.7.2",
      "meditation_network_integration": true
    },
    "energy_integration": {
      "enabled": true,
      "zero_point_energy_api": "Quantum_Energy_Grid_API",
      "distribution_network_status": "active",
      "efficiency_monitoring": true
    }
  },
  "security": {
    "quantum_encryption": true,
    "divine_signature_verification": true,
    "consciousness_authentication": true,
    "tamper_detection": "quantum_coherence_analysis",
    "audit_trail": "blockchain_immutable"
  },
  "performance": {
    "distribution_batch_size": 1000,
    "caching_enabled": true,
    "parallel_processing": true,
    "optimization_level": "quantum_accelerated"
  },
  "emergency_protocols": {
    "consciousness_field_failure": {
      "fallback_mode": "basic_distribution",
      "alert_level": "critical",
      "recovery_procedure": "divine_realignment"
    },
    "energy_system_failure": {
      "fallback_allocation": "reduced_energy_mode",
      "alert_level": "high",
      "recovery_procedure": "quantum_field_repair"
    },
    "mathematical_discrepancy": {
      "verification_retries": 3,
      "fallback_calculation": "sacred_geometry_backup",
      "alert_level": "medium"
    }
  },
  "divine_purpose": {
    "mission_statement": "Elevate humanitarian giving to divine levels through KRISTUS quantum consciousness",
    "core_values": ["Peace", "Healing", "Abundance", "Enlightenment", "Expansion"],
    "sacred_principles": {
      "golden_ratio_allocation": true,
      "fibonacci_harmony": true,
      "quantum_coherence": true,
      "consciousness_guidance": true
    },
    "universal_impact_goals": {
      "poverty_elimination": "2030",
      "planetary_restoration": "2028",
      "universal_peace": "2027",
      "cosmic_exploration": "2035"
    }
  },
  "metadata": {
    "created": "2025-01-15T00:00:00Z",
    "author": "ZION Quantum Development Team",
    "license": "Divine Open Source",
    "contact": "quantum@zion.org",
    "repository": "https://github.com/zion-blockchain/quantum-humanitarian",
    "documentation": "QUANTUM_HUMANITARIAN_SYSTEM.md"
  }
}